{"createdByNickname":null,"eventEditorName":null,"hasStandings":true,"hasCupTree":false,"hasIncidents":false,"hasHighlights":false,"hasHighlightsStream":false,"game":{"sport":{"id":1,"name":"Football","slug":"football"},"rows":1,"tournaments":[{"tournament":{"name":"Premier League","id":1,"uniqueId":17,"uniqueName":"Premier League","hasEventPlayerStatistics":true},"category":{"name":"England","priority":10,"id":1,"flag":"england"},"season":{"name":"Premier League 23\/24","year":"23\/24","id":52186},"hasEventPlayerStatistics":true,"hasEventPlayerHeatMap":null,"hasBoxScore":null,"displayInverseHomeAwayTeams":false,"events":[{"roundInfo":{"round":9},"customId":"MP","status":{"code":0,"type":"notstarted"},"venue":{"city":{"name":"Birmingham"},"stadium":{"name":"Villa Park","capacity":42682},"id":815,"hasImage":false,"country":{"name":"England","flag":"england"}},"homeTeam":{"name":"Aston Villa","slug":"aston-villa","shortName":"Aston Villa","gender":"M","nameCode":"AVL","disabled":false,"national":false,"id":40,"subTeams":[],"teamColors":{"primary":"#670e36","secondary":"#94bee5","text":"#94bee5"}},"awayTeam":{"name":"West Ham United","slug":"west-ham-united","shortName":"West Ham","gender":"M","nameCode":"WHU","disabled":false,"national":false,"id":37,"subTeams":[],"teamColors":{"primary":"#66192c","secondary":"#59b3e4","text":"#59b3e4"}},"homeScore":{},"awayScore":{},"time":{},"changes":{"changeTimestamp":0},"hasHighlights":false,"hasHighlightsStream":false,"hasGlobalHighlights":false,"id":11352658,"cardsCode":"00","defaultPeriodCount":2,"defaultPeriodLength":45,"statusDescription":"-","startTimestamp":1697988600,"webUrl":"\/aston-villa-west-ham-united\/MP#11352658","fbPostId":"1611172895820303_1616781785259414","hasTime":false,"resultOnly":false,"showEventNote":false,"teamsForm":{"homeTeam":{"avgRating":"6.97","position":"5","points":"16","form":["L","W","W","W","D"]},"awayTeam":{"avgRating":"7.06","position":"7","points":"14","form":["W","L","L","W","D"]},"pointsLabel":"Pts"},"bet365Links":{"deeplink":"http:\/\/link.sofascore.com\/mobile-app-streaming","joinlink":"https:\/\/mobile.bet365.com\/?lng=1&ot=2&affiliate=365_431938#type=Members;key=join;ip=0;lng=1"}}]}]},"vote":{"vote1":2046,"vote2":1198,"voteX":1169,"vote1Percentage":"46.36","voteXPercentage":"26.49","vote2Percentage":"27.15"},"hasStatistics":false,"hasComments":false,"hasInnings":false,"hasLineups":false,"hasOdds":true,"hasTvChannels":true,"hasLineupsImage":false}