{"createdByNickname":null,"eventEditorName":null,"hasStandings":true,"hasCupTree":false,"hasIncidents":false,"hasHighlights":false,"hasHighlightsStream":false,"game":{"sport":{"id":1,"name":"Football","slug":"football"},"rows":1,"tournaments":[{"tournament":{"name":"Premier League","id":1,"uniqueId":17,"uniqueName":"Premier League","hasEventPlayerStatistics":true},"category":{"name":"England","priority":10,"id":1,"flag":"england"},"season":{"name":"Premier League 23\/24","year":"23\/24","id":52186},"hasEventPlayerStatistics":true,"hasEventPlayerHeatMap":null,"hasBoxScore":null,"displayInverseHomeAwayTeams":false,"events":[{"roundInfo":{"round":13},"customId":"hsxb","status":{"code":0,"type":"notstarted"},"venue":{"city":{"name":"Luton"},"stadium":{"name":"Kenilworth Road","capacity":10226},"id":2178,"hasImage":false,"country":{"name":"England","flag":"england"}},"homeTeam":{"name":"Luton Town","slug":"luton-town","shortName":"Luton","gender":"M","nameCode":"LUT","disabled":false,"national":false,"id":72,"subTeams":[],"teamColors":{"primary":"#ff3300","secondary":"#000033","text":"#000033"}},"awayTeam":{"name":"Crystal Palace","slug":"crystal-palace","shortName":"Crystal Palace","gender":"M","nameCode":"CRY","disabled":false,"national":false,"id":7,"subTeams":[],"teamColors":{"primary":"#0033ff","secondary":"#b90d2b","text":"#b90d2b"}},"homeScore":{},"awayScore":{},"time":{},"changes":{"changeTimestamp":0},"hasHighlights":false,"hasHighlightsStream":false,"hasGlobalHighlights":false,"id":11352370,"cardsCode":"00","defaultPeriodCount":2,"defaultPeriodLength":45,"statusDescription":"-","startTimestamp":1700924400,"webUrl":"\/luton-town-crystal-palace\/hsxb#11352370","fbPostId":"1611172895820303_1616781785259414","hasTime":false,"resultOnly":false,"showEventNote":false,"bet365Links":{"deeplink":"http:\/\/link.sofascore.com\/mobile-app-streaming","joinlink":"https:\/\/mobile.bet365.com\/?lng=1&ot=2&affiliate=365_431938#type=Members;key=join;ip=0;lng=1"}}]}]},"vote":{"vote1":66,"vote2":96,"voteX":15,"vote1Percentage":"37.29","voteXPercentage":"8.47","vote2Percentage":"54.24"},"hasStatistics":false,"hasComments":false,"hasInnings":false,"hasLineups":false,"hasOdds":true,"hasTvChannels":true,"hasLineupsImage":false}